PIauthorizer/__init__.py
PIauthorizer/autorest/__init__.py
PIauthorizer/autorest/create_autorest_schema.py
PIauthorizer/autorest/format_operation_ids.py
PIauthorizer/ConfigManager/__init__.py
PIauthorizer/ConfigManager/ConfigManager.py
PIauthorizer/ConfigManager/Configuration.py
PIauthorizer/ConfigManager/ConfigurationTemplate.py
PIauthorizer/ConfigManager/credential_templates/GoogleTranslateCredentials.json
PIauthorizer/ConfigManager/credential_templates/ModelManager.json
PIauthorizer/ConfigManager/credential_templates/ModelManagerAnnotation.json
PIauthorizer/ConfigManager/credential_templates/NerAnnotation.json
PIauthorizer/ConfigManager/credential_templates/NerLabelOntologyMapping.json
PIauthorizer/ConfigManager/credential_templates/SRLCorefParameters.json
PIauthorizer/ConfigManager/credential_templates/WARNING.txt
PIauthorizer/ConfigManager/Forms.py
PIauthorizer/ConfigManager/logging/logging.conf
PIauthorizer/functional/__init__.py
PIauthorizer/functional/readiness_router.py
PIauthorizer/functional/StressTester.py
PIauthorizer/logging/__init__.py
PIauthorizer/logging/get_logging_config.py
PIauthorizer/logging/logged_route.py
piauthorizer-1.2.4.dist-info/WHEEL
piauthorizer-1.2.4.dist-info/METADATA
piauthorizer-1.2.4.dist-info/RECORD
